regression_bias_corrector/__init__.py
regression_bias_corrector/_version.py
regression_bias_corrector/linear_corrector.py
regression_bias_corrector-0.0.2.dist-info/METADATA
regression_bias_corrector-0.0.2.dist-info/WHEEL
regression_bias_corrector-0.0.2.dist-info/RECORD
