Metadata-Version: 2.3
Name: regression-bias-corrector
Version: 0.0.2
Summary: Bias correction of regression ML models
Project-URL: Homepage, https://github.com/mike-live/regression-bias-corrector
Project-URL: Bug Tracker, https://github.com/mike-live/regression-bias-corrector/issues
Author-email: Mikhail Krivonosov <krivonosov@itmm.unn.ru>
Classifier: Operating System :: OS Independent
Classifier: Programming Language :: Python :: 3
Requires-Python: >=3.7
Requires-Dist: numpy>=1.15.0
Requires-Dist: pyyaml
Requires-Dist: scikit-learn
